{
  "schema": 1,
  "kind": "movp_catalog_manifest",
  "environment": "prod",
  "generatedAtDeviceMs": 1784709404631,
  "config_gz": {
    "prod": {
      "activeFilename": "items_up_r1784709388629.json.gz",
      "releaseId": "1784709388629",
      "enabled": true,
      "mirrors": {
        "server1": true,
        "server2": true,
        "github": true
      },
      "urls": {
        "server1": "https:\/\/api.appsdevxp.com\/db\/items_up_r1784709388629.json.gz",
        "server2": "https:\/\/developerxploit.com\/app\/db\/items_up_r1784709388629.json.gz",
        "github": "https:\/\/raw.githubusercontent.com\/dev-mplus01\/mplus01T\/main\/db\/list\/items_up_r1784709388629.json.gz"
      },
      "truthSource": {
        "target": "server2",
        "url": "https:\/\/developerxploit.com\/app\/db\/items_up_r1784709388629.json.gz",
        "filename": "items_up_r1784709388629.json.gz"
      },
      "encoding": "gzip",
      "compressedSizeBytes": 4348492,
      "compressedSha256": "9c15481da4564d67e320a481a724887d61ac46f27e69e10d2560fb0d8fcaa67e",
      "uncompressedSizeBytes": 9661829,
      "uncompressedSha256": "4d86623ff1e4bdbd2083f06eb0cad2609d761a505e712e26d21d262791ee885d",
      "updatedAtDeviceMs": 1784709404631,
      "publishedAtDeviceMs": 1784709404631,
      "catalog": {
        "filename": "items_up_r1784709388629.json.gz",
        "encoding": "gzip",
        "compressedSizeBytes": 4348492,
        "compressedSha256": "9c15481da4564d67e320a481a724887d61ac46f27e69e10d2560fb0d8fcaa67e",
        "uncompressedSizeBytes": 9661829,
        "uncompressedSha256": "4d86623ff1e4bdbd2083f06eb0cad2609d761a505e712e26d21d262791ee885d"
      }
    }
  }
}
