{
  "schema": 1,
  "kind": "movp_catalog_manifest",
  "environment": "prod",
  "generatedAtDeviceMs": 1779244350014,
  "config_gz": {
    "prod": {
      "activeFilename": "items_up_r1779244349959.json.gz",
      "releaseId": "1779244349959",
      "enabled": true,
      "mirrors": {
        "server1": true,
        "server2": true,
        "github": true
      },
      "urls": {
        "server1": "https:\/\/api.appsdevxp.com\/db\/items_up_r1779244349959.json.gz",
        "server2": "https:\/\/developerxploit.com\/app\/db\/items_up_r1779244349959.json.gz",
        "github": "https:\/\/raw.githubusercontent.com\/dev-mplus01\/mplus01T\/main\/db\/list\/items_up_r1779244349959.json.gz"
      },
      "encoding": "gzip",
      "compressedSizeBytes": 4229140,
      "compressedSha256": "c757ebf577990bf8dc003a607c9f1b40d62886832194fe5cf3014da6d8714964",
      "uncompressedSizeBytes": 9403009,
      "uncompressedSha256": "3c979b2cda31972c04f7d6c501fa29d795e640b6e8d49fb9f94e494ac5f49a4e",
      "updatedAtDeviceMs": 1779244350014,
      "publishedAtDeviceMs": 1779244350014,
      "catalog": {
        "filename": "items_up_r1779244349959.json.gz",
        "encoding": "gzip",
        "compressedSizeBytes": 4229140,
        "compressedSha256": "c757ebf577990bf8dc003a607c9f1b40d62886832194fe5cf3014da6d8714964",
        "uncompressedSizeBytes": 9403009,
        "uncompressedSha256": "3c979b2cda31972c04f7d6c501fa29d795e640b6e8d49fb9f94e494ac5f49a4e"
      }
    }
  }
}
